tblink_rpc_core/endpoint_services.py
tblink_rpc_core/interface_inst.py
tblink_rpc_core/param_val_int.py
tblink_rpc_core/transport.py
tblink_rpc_core/endpoint_event.py
tblink_rpc_core/native.cpython-310-x86_64-linux-gnu.so
tblink_rpc_core/endpoint.py
tblink_rpc_core/type_map.py
tblink_rpc_core/endpoint_base.py
tblink_rpc_core/param_val.py
tblink_rpc_core/endpoint_mgr_listener.py
tblink_rpc_core/param_val_str.py
tblink_rpc_core/param_val_bool.py
tblink_rpc_core/type.py
tblink_rpc_core/launch_type.py
tblink_rpc_core/interface_impl_factory.py
tblink_rpc_core/endpoint_listener.py
tblink_rpc_core/endpoint_msg_transport.py
tblink_rpc_core/method_type_builder.py
tblink_rpc_core/invoke_rsp_waiter.py
tblink_rpc_core/method_e.py
tblink_rpc_core/__init__.py
tblink_rpc_core/interface_type_builder.py
tblink_rpc_core/method_type.py
tblink_rpc_core/endpoint_mgr.py
tblink_rpc_core/type_int.py
tblink_rpc_core/tblink_event.py
tblink_rpc_core/param_val_visitor.py
tblink_rpc_core/param_decl.py
tblink_rpc_core/interface_inst_msg_transport.py
tblink_rpc_core/type_vec.py
tblink_rpc_core/interface_type.py
tblink_rpc_core/tblink_listener.py
tblink_rpc_core/transport_json_socket.py
tblink_rpc_core/param_val_map.py
tblink_rpc_core/event_type_e.py
tblink_rpc_core/param_val_vec.py
tblink_rpc_core/transport_dual_fifo.py
tblink_rpc_core/tblink.py
tblink_rpc_core/type_e.py
tblink_rpc_core-0.0.1.3223308326.dist-info/top_level.txt
tblink_rpc_core-0.0.1.3223308326.dist-info/entry_points.txt
tblink_rpc_core-0.0.1.3223308326.dist-info/LICENSE
tblink_rpc_core-0.0.1.3223308326.dist-info/METADATA
tblink_rpc_core-0.0.1.3223308326.dist-info/RECORD
tblink_rpc_core-0.0.1.3223308326.dist-info/WHEEL
